CHANGELOG.txt
LICENSE.txt
MANIFEST.in
README.txt
new 2.py
protect.txt
setup.py
vanity.py
fymjosh/__init__.py
fymjosh.egg-info/PKG-INFO
fymjosh.egg-info/SOURCES.txt
fymjosh.egg-info/dependency_links.txt
fymjosh.egg-info/requires.txt
fymjosh.egg-info/top_level.txt