Metadata-Version: 2.1
Name: fymjosh
Version: 1.0.7
Summary: A library that focuses on customization of console and discord
Home-page: UNKNOWN
Author: fymjosh
Author-email: lone.cord12@gmail.com
License: MIT
Keywords: discord,console
Platform: UNKNOWN
Classifier: Development Status :: 5 - Production/Stable
Classifier: Intended Audience :: Education
Classifier: Operating System :: Microsoft :: Windows :: Windows 10
Classifier: License :: OSI Approved :: MIT License
Classifier: Programming Language :: Python :: 3
License-File: LICENSE.txt
